jlabdev/__init__.py
jlabdev/main.py
jlabdev-20230119.dist-info/LICENSE
jlabdev-20230119.dist-info/METADATA
jlabdev-20230119.dist-info/WHEEL
jlabdev-20230119.dist-info/entry_points.txt
jlabdev-20230119.dist-info/top_level.txt
jlabdev-20230119.dist-info/RECORD
