Metadata-Version: 2.1
Name: jlabdev
Version: 20230119
Summary: A small simple tool to develop python from jupyterlab notebooks.
Home-page: https://github.com/penguinmenac3/jlabdev
Download-URL: https://github.com/penguinmenac3/jlabdev/tarball/20230119
Author: Michael Fuerst
Author-email: mail@michaelfuerst.de
License: MIT
Classifier: Development Status :: 3 - Alpha
Classifier: Intended Audience :: Developers
Classifier: Programming Language :: Python
License-File: LICENSE
